svgnarrative/__init__.py
svgnarrative/model.py
svgnarrative-0.0.4.dist-info/licenses/LICENSE
svgnarrative-0.0.4.dist-info/METADATA
svgnarrative-0.0.4.dist-info/WHEEL
svgnarrative-0.0.4.dist-info/top_level.txt
svgnarrative-0.0.4.dist-info/RECORD
